keggstand/__init__.py
keggstand/api.py
keggstand/parsers.py
keggstand-0.0.7.dist-info/AUTHORS.rst
keggstand-0.0.7.dist-info/LICENSE
keggstand-0.0.7.dist-info/METADATA
keggstand-0.0.7.dist-info/WHEEL
keggstand-0.0.7.dist-info/top_level.txt
keggstand-0.0.7.dist-info/RECORD
