Metadata-Version: 2.1
Name: keggstand
Version: 0.0.7
Summary: KEGG API client and parsers for pathway protein-protein interactions
Home-page: https://github.com/daniaki/keggstand
Author: Daniel Esposito
Author-email: danielce90@gmail.com
License: MIT license
Keywords: keggstand
Platform: UNKNOWN
Classifier: Development Status :: 2 - Pre-Alpha
Classifier: Intended Audience :: Developers
Classifier: License :: OSI Approved :: MIT License
Classifier: Natural Language :: English
Classifier: Programming Language :: Python :: 3
Classifier: Programming Language :: Python :: 3.6
Classifier: Programming Language :: Python :: 3.7
Classifier: Programming Language :: Python :: 3.8
Requires-Python: >=3.6
Requires-Dist: beautifulsoup4 (>=4.8)
Requires-Dist: lxml (>=4.4)
Requires-Dist: pandas (>=1.0)
Requires-Dist: requests (>=2.20)
Requires-Dist: tqdm (>=4.48.0)
